LICENSE
MANIFEST.in
README.rst
scott_freeze.py
setup.py
scott_freeze.egg-info/PKG-INFO
scott_freeze.egg-info/SOURCES.txt
scott_freeze.egg-info/dependency_links.txt
scott_freeze.egg-info/entry_points.txt
scott_freeze.egg-info/not-zip-safe
scott_freeze.egg-info/top_level.txt