Metadata-Version: 1.1
Name: scott-freeze
Version: 0.1
Summary: Utility for managing requirements files
Home-page: http://github.com/onefinestay/scott-freeze
Author: onefinestay
Author-email: engineering@onefinestay.com
License: Apache License, Version 2.0
Platform: UNKNOWN
Classifier: Programming Language :: Python :: 2
Classifier: Programming Language :: Python :: 2.7
Classifier: Programming Language :: Python :: 3
Classifier: Programming Language :: Python :: 3.3
Classifier: Programming Language :: Python :: 3.4
Classifier: Operating System :: MacOS :: MacOS X
Classifier: Operating System :: POSIX
Classifier: Programming Language :: Python :: 2.7
Classifier: Intended Audience :: Developers
